README.md
setup.py
simest.py
Simest.egg-info/PKG-INFO
Simest.egg-info/SOURCES.txt
Simest.egg-info/dependency_links.txt
Simest.egg-info/top_level.txt