Metadata-Version: 2.1
Name: Simest
Version: 1.1
Summary: Simest - Simple and small code testing library for Python 3.8+
Home-page: https://pikostudios.dev
Author: cookieguy
Author-email: mail@frankiee.me
License: MIT
Platform: UNKNOWN
